README-generated.md
cloudreactor_api_client/__init__.py
cloudreactor_api_client/api/__init__.py
cloudreactor_api_client/api/alert_methods/__init__.py
cloudreactor_api_client/api/alert_methods/alert_methods_clone_create.py
cloudreactor_api_client/api/alert_methods/alert_methods_create.py
cloudreactor_api_client/api/alert_methods/alert_methods_destroy.py
cloudreactor_api_client/api/alert_methods/alert_methods_list.py
cloudreactor_api_client/api/alert_methods/alert_methods_partial_update.py
cloudreactor_api_client/api/alert_methods/alert_methods_retrieve.py
cloudreactor_api_client/api/alert_methods/alert_methods_update.py
cloudreactor_api_client/api/email_notification_profiles/__init__.py
cloudreactor_api_client/api/email_notification_profiles/email_notification_profiles_clone_create.py
cloudreactor_api_client/api/email_notification_profiles/email_notification_profiles_create.py
cloudreactor_api_client/api/email_notification_profiles/email_notification_profiles_destroy.py
cloudreactor_api_client/api/email_notification_profiles/email_notification_profiles_list.py
cloudreactor_api_client/api/email_notification_profiles/email_notification_profiles_partial_update.py
cloudreactor_api_client/api/email_notification_profiles/email_notification_profiles_retrieve.py
cloudreactor_api_client/api/email_notification_profiles/email_notification_profiles_update.py
cloudreactor_api_client/api/pagerduty_profiles/__init__.py
cloudreactor_api_client/api/pagerduty_profiles/pagerduty_profiles_clone_create.py
cloudreactor_api_client/api/pagerduty_profiles/pagerduty_profiles_create.py
cloudreactor_api_client/api/pagerduty_profiles/pagerduty_profiles_destroy.py
cloudreactor_api_client/api/pagerduty_profiles/pagerduty_profiles_list.py
cloudreactor_api_client/api/pagerduty_profiles/pagerduty_profiles_partial_update.py
cloudreactor_api_client/api/pagerduty_profiles/pagerduty_profiles_retrieve.py
cloudreactor_api_client/api/pagerduty_profiles/pagerduty_profiles_update.py
cloudreactor_api_client-0.3.1.3.dist-info/LICENSE
cloudreactor_api_client-0.3.1.3.dist-info/WHEEL
cloudreactor_api_client-0.3.1.3.dist-info/METADATA
cloudreactor_api_client-0.3.1.3.dist-info/RECORD
