Metadata-Version: 2.1
Name: cloudreactor-api-client
Version: 0.3.1.3
Summary: A client library for accessing the CloudReactor API, which monitors and manages Tasks and Workflows.
Home-page: https://cloudreactor.io
License: BSD 2-Clause
Author: Jeff Tsay
Author-email: jeff@cloudreactor.io
Requires-Python: >=3.7,<4.0
Classifier: Development Status :: 4 - Beta
Classifier: Intended Audience :: Developers
Classifier: License :: Other/Proprietary License
Classifier: Natural Language :: English
Classifier: Operating System :: OS Independent
Classifier: Programming Language :: Python :: 3
Classifier: Programming Language :: Python :: 3.7
Classifier: Programming Language :: Python :: 3.8
Classifier: Programming Language :: Python :: 3.9
Classifier: Topic :: Software Development :: Libraries
Provides-Extra: docs
Requires-Dist: attrs (>=21.3.0)
Requires-Dist: httpx (>=0.15.4,<0.23.0)
Requires-Dist: python-dateutil (>=2.8.0,<3.0.0)
Project-URL: Bug Tracker, https://github.com/CloudReactor/cloudreactor-python-api-client/issues
Project-URL: Repository, https://github.com/CloudReactor/cloudreactor-python-api-client/cloudreactor-api-client
